{"Client":{"Client_Name":"김지은","NickName":"mind75e"},"History":[{"Date":"2023-01-31T12:57:13.658675+09:00","ProductList":[{"Option":{"Id":26,"Name":"레드라벨 레이어드메모지","Option_Id":0,"Option_Name":"기본","OneBox_Total_Count":50,"Person_Per_Count":10,"Person_Per_Price":143},"Count":1},{"Option":{"Id":27,"Name":"길쭉레이아드","Option_Id":1,"Option_Name":"그린","OneBox_Total_Count":30,"Person_Per_Count":5,"Person_Per_Price":189},"Count":1},{"Option":{"Id":5,"Name":"중세프레임떡메","Option_Id":1,"Option_Name":"네이비","OneBox_Total_Count":30,"Person_Per_Count":5,"Person_Per_Price":153},"Count":1}]}]}