{"Client":{"Client_Name":"우혜진","NickName":"jsmz4107"},"History":[{"Date":"2023-06-17T14:42:55.969873+09:00","ProductList":[{"Option":{"Id":129,"Name":"5판박이스티커","Option_Id":1,"Option_Name":"브라운","OneBox_Total_Count":2,"Person_Per_Count":1,"Person_Per_Price":500},"Count":2},{"Option":{"Id":128,"Name":"5퍼플꽃스티커","Option_Id":0,"Option_Name":"기본","OneBox_Total_Count":3,"Person_Per_Count":1,"Person_Per_Price":243},"Count":3},{"Option":{"Id":137,"Name":"6블랙 칼선스티커","Option_Id":1,"Option_Name":"꽃","OneBox_Total_Count":1,"Person_Per_Count":1,"Person_Per_Price":505},"Count":1},{"Option":{"Id":138,"Name":"6실사 사각스티커","Option_Id":2,"Option_Name":"브라운","OneBox_Total_Count":1,"Person_Per_Count":1,"Person_Per_Price":505},"Count":1},{"Option":{"Id":126,"Name":"5화지레터링","Option_Id":1,"Option_Name":"레터링","OneBox_Total_Count":4,"Person_Per_Count":1,"Person_Per_Price":148},"Count":4}]},{"Date":"2023-05-22T11:26:02.206863+09:00","ProductList":[{"Option":{"Id":112,"Name":"5하트보석스티커","Option_Id":0,"Option_Name":"기본","OneBox_Total_Count":1,"Person_Per_Count":1,"Person_Per_Price":534},"Count":1},{"Option":{"Id":111,"Name":"5뽀짝스티커","Option_Id":0,"Option_Name":"기본","OneBox_Total_Count":6,"Person_Per_Count":3,"Person_Per_Price":476},"Count":2},{"Option":{"Id":109,"Name":"5영문마테","Option_Id":2,"Option_Name":"화이트","OneBox_Total_Count":200,"Person_Per_Count":200,"Person_Per_Price":875},"Count":1},{"Option":{"Id":99,"Name":"4우주엠보싱스티커","Option_Id":4,"Option_Name":"조개","OneBox_Total_Count":1,"Person_Per_Count":1,"Person_Per_Price":654},"Count":1}]}]}